gmaps_image_fetcher/__init__.py
gmaps_image_fetcher/main.py
gmaps_image_fetcher-1.0.0.dist-info/licenses/LICENSE
gmaps_image_fetcher-1.0.0.dist-info/METADATA
gmaps_image_fetcher-1.0.0.dist-info/WHEEL
gmaps_image_fetcher-1.0.0.dist-info/entry_points.txt
gmaps_image_fetcher-1.0.0.dist-info/top_level.txt
gmaps_image_fetcher-1.0.0.dist-info/RECORD
