Metadata-Version: 2.4
Name: gmaps-image-fetcher
Version: 1.0.0
Summary: Stitch together Google Maps images from lat, long coordinates using the Static Maps API.
Home-page: https://github.com/joseph-holland/gmaps-image-fetcher
Author: Joseph Holland
Author-email: Joseph Holland <joseph@josephholland.ie>
License: GNU General Public License v3.0
Project-URL: Homepage, https://github.com/joseph-holland/gmaps-image-fetcher
Project-URL: Bug Tracker, https://github.com/joseph-holland/gmaps-image-fetcher/issues
Classifier: Programming Language :: Python :: 3
Classifier: License :: OSI Approved :: GNU General Public License v3 or later (GPLv3+)
Classifier: Operating System :: OS Independent
Requires-Python: >=3.5
License-File: LICENSE
Requires-Dist: requests
Requires-Dist: Pillow
Dynamic: author
Dynamic: home-page
Dynamic: license-file
Dynamic: requires-python
